ansible_parser/__init__.py
ansible_parser/logs.py
ansible_parser/play.py
ansible_parser/tasks.py
test/__init__.py
test/test_logs.py
test/test_play.py
test/test_task.py
ansible_output_parser-0.1.0.dist-info/LICENSE
ansible_output_parser-0.1.0.dist-info/METADATA
ansible_output_parser-0.1.0.dist-info/WHEEL
ansible_output_parser-0.1.0.dist-info/top_level.txt
ansible_output_parser-0.1.0.dist-info/RECORD
