Metadata-Version: 2.1
Name: ansible-output-parser
Version: 0.1.0
Summary: Parser for Ansible output
Home-page: https://github.com/RockProfile/Ansible-Output-Parser
Author: Peter McDonald
Author-email: admin@rockprofile.com
Project-URL: Bug Tracker, https://github.com/RockProfile/Ansible-Output-Parser/issues
Project-URL: Source, https://github.com/RockProfile/Ansible-Output-Parser
Classifier: Programming Language :: Python :: 3.9
Classifier: Programming Language :: Python :: 3.10
Classifier: Programming Language :: Python :: 3.11
Classifier: License :: OSI Approved :: MIT License
Classifier: Operating System :: OS Independent
Classifier: Intended Audience :: Developers
Classifier: Development Status :: 4 - Beta
Requires-Python: >=3.9
License-File: LICENSE
Provides-Extra: build
Requires-Dist: wheel ; extra == 'build'
Requires-Dist: build ; extra == 'build'
Provides-Extra: test
Requires-Dist: black ; extra == 'test'
Requires-Dist: flake8 ; extra == 'test'
Requires-Dist: isort ; extra == 'test'
Requires-Dist: mypy ; extra == 'test'
Requires-Dist: pytest ; extra == 'test'
Requires-Dist: twine ; extra == 'test'
Requires-Dist: wheel ; extra == 'test'
